webview/__init__.py
webview/_dummy_holder.c
webview/_dummy_holder.cpython-311-aarch64-linux-gnu.so
webview/_webview_ffi.py
webview/webview.py
webview_python-1.1.2.dist-info/METADATA
webview_python-1.1.2.dist-info/WHEEL
webview_python-1.1.2.dist-info/top_level.txt
webview_python-1.1.2.dist-info/RECORD
webview_python-1.1.2.dist-info/licenses/LICENSE
