Metadata-Version: 2.4
Name: webview_python
Version: 1.1.2
Summary: Python bindings for the webview library, which completely follow deno_webview design and principles
License: MIT License
Project-URL: Homepage, https://github.com/congzhangzh/webview_python
Project-URL: Repository, https://github.com/congzhangzh/webview_python.git
Project-URL: Bug Tracker, https://github.com/congzhangzh/webview_python/issues
Keywords: webview,gui,desktop,application,html,web
Classifier: Development Status :: 3 - Alpha
Classifier: Intended Audience :: Developers
Classifier: License :: OSI Approved :: MIT License
Classifier: Operating System :: OS Independent
Classifier: Programming Language :: Python
Classifier: Programming Language :: Python :: 3.10
Classifier: Programming Language :: Python :: 3.11
Classifier: Programming Language :: Python :: 3.12
Classifier: Programming Language :: Python :: 3.13
Classifier: Programming Language :: Python :: 3.14
Classifier: Programming Language :: Python :: Implementation :: CPython
Classifier: Programming Language :: Python :: Implementation :: PyPy
Classifier: Topic :: Software Development :: Libraries :: Python Modules
Classifier: Topic :: Software Development :: User Interfaces
Requires-Python: >=3.10
License-File: LICENSE
Dynamic: license-file
